README.rst
setup.cfg
setup.py
src/tctalker/__init__.py
src/tctalker/tctalker.py
src/tctalker.egg-info/PKG-INFO
src/tctalker.egg-info/SOURCES.txt
src/tctalker.egg-info/dependency_links.txt
src/tctalker.egg-info/entry_points.txt
src/tctalker.egg-info/requires.txt
src/tctalker.egg-info/top_level.txt