Metadata-Version: 1.0
Name: tctalker
Version: 0.1.0
Summary: Script to perform various ops against TC API
Home-page: https://github.com/MihaiTabara/tctalker
Author: Mihai Tabara
Author-email: mtabara@mozilla.com
License: MPL
Keywords: taskcluster api cli tool
Platform: UNKNOWN
